Metadata-Version: 1.2
Name: cbcvalidator
Version: 0.0.7
Summary: A package to help validate limits in a dataframe column
Home-page: https://github.com/Cold-Bore-Capital/cbcvalidator
Author: Cold Bore Capital
Author-email: it-group@coldborecapital.com
License: UNKNOWN
Platform: UNKNOWN
Classifier: Programming Language :: Python :: 3.8
Classifier: Topic :: Software Development :: Libraries :: Python Modules
Classifier: Development Status :: 4 - Beta
Requires-Python: >=3.8
